MANIFEST.in
setup.cfg
setup.py
easy_karabiner/__init__.py
easy_karabiner/__main__.py
easy_karabiner/alias.py
easy_karabiner/basexml.py
easy_karabiner/config.py
easy_karabiner/def_tag_map.py
easy_karabiner/definition.py
easy_karabiner/exception.py
easy_karabiner/factory.py
easy_karabiner/filter.py
easy_karabiner/fucking_string.py
easy_karabiner/generator.py
easy_karabiner/keycombo.py
easy_karabiner/keymap.py
easy_karabiner/main.py
easy_karabiner/osxkit.py
easy_karabiner/parse.py
easy_karabiner/query.py
easy_karabiner/util.py
easy_karabiner.egg-info/PKG-INFO
easy_karabiner.egg-info/SOURCES.txt
easy_karabiner.egg-info/dependency_links.txt
easy_karabiner.egg-info/entry_points.txt
easy_karabiner.egg-info/requires.txt
easy_karabiner.egg-info/top_level.txt
easy_karabiner/data/alias.data
easy_karabiner/data/def_tag_map.data