Metadata-Version: 1.1
Name: easy-karabiner
Version: 0.5.2
Summary: A tool to simplify key-remapping configuration for Karabiner
Home-page: https://github.com/loggerhead/Easy-Karabiner
Author: loggerhead
Author-email: i@loggerhead.me
License: MIT
Keywords: Karabiner,configer,remap,key
Platform: UNKNOWN
Classifier: Development Status :: 4 - Beta
Classifier: License :: OSI Approved :: MIT License
Classifier: Intended Audience :: Developers
Classifier: Intended Audience :: End Users/Desktop
Classifier: Operating System :: MacOS
Classifier: Programming Language :: Python
Classifier: Programming Language :: Python :: 2
Classifier: Programming Language :: Python :: 2.7
Classifier: Programming Language :: Python :: 3
Classifier: Programming Language :: Python :: 3.3
Classifier: Programming Language :: Python :: 3.4
Classifier: Programming Language :: Python :: 3.5
Classifier: Topic :: Utilities
